openinference/instrumentation/autogen_agentchat/__init__.py
openinference/instrumentation/autogen_agentchat/_wrappers.py
openinference/instrumentation/autogen_agentchat/py.typed
openinference/instrumentation/autogen_agentchat/version.py
openinference_instrumentation_autogen_agentchat-0.1.6.dist-info/METADATA
openinference_instrumentation_autogen_agentchat-0.1.6.dist-info/WHEEL
openinference_instrumentation_autogen_agentchat-0.1.6.dist-info/entry_points.txt
openinference_instrumentation_autogen_agentchat-0.1.6.dist-info/licenses/LICENSE
openinference_instrumentation_autogen_agentchat-0.1.6.dist-info/RECORD
